mtga/__init__.py
mtga/_version.py
mtga/models/__init__.py
mtga/models/card.py
mtga/models/card_set.py
mtga/set_data/__init__.py
mtga/set_data/aer.py
mtga/set_data/akh.py
mtga/set_data/ana.py
mtga/set_data/arenasup.py
mtga/set_data/bfz.py
mtga/set_data/dom.py
mtga/set_data/dynamic.py
mtga/set_data/eld.py
mtga/set_data/grn.py
mtga/set_data/hou.py
mtga/set_data/kld.py
mtga/set_data/m19.py
mtga/set_data/m20.py
mtga/set_data/mi.py
mtga/set_data/rix.py
mtga/set_data/rna.py
mtga/set_data/roe.py
mtga/set_data/rtr.py
mtga/set_data/w17.py
mtga/set_data/war.py
mtga/set_data/weird.py
mtga/set_data/xln.py
MTGA-0.9.5.dist-info/LICENSE
MTGA-0.9.5.dist-info/METADATA
MTGA-0.9.5.dist-info/WHEEL
MTGA-0.9.5.dist-info/entry_points.txt
MTGA-0.9.5.dist-info/top_level.txt
MTGA-0.9.5.dist-info/RECORD
