Metadata-Version: 2.1
Name: MTGA
Version: 0.9.5
Summary: python-mtga: a python-accessible interface for MTGA cards
Home-page: https://github.com/mtgatracker/python-mtga
Author: shawkins
Author-email: devs.mtgatracker@gmail.com
License: MIT License
Keywords: mtga mtg magic arena grpid mtgjson
Platform: UNKNOWN
Classifier: Development Status :: 3 - Alpha
Classifier: Intended Audience :: Developers
Classifier: Topic :: Software Development :: Testing
Classifier: Topic :: Software Development :: Quality Assurance
Classifier: Programming Language :: Python :: 3
Classifier: Programming Language :: Python :: 3.5
Classifier: Programming Language :: Python :: 3.6
Provides-Extra: dev
Provides-Extra: test
